drewcopytools/__init__.py
drewcopytools/datetimetools.py
drewcopytools/filetools.py
drewcopytools/jsontools.py
drewcopytools/logtools.py
drewcopytools/tools.py
drewcopytools-0.3.8.dist-info/LICENSE
drewcopytools-0.3.8.dist-info/WHEEL
drewcopytools-0.3.8.dist-info/METADATA
drewcopytools-0.3.8.dist-info/RECORD
